pa_trading/__init__.py
pa_trading/_pb/__init__.py
pa_trading/_pb/pullback.py
pa_trading/b.py
pa_trading/conf.py
pa_trading/l.py
pa_trading/p2.py
pa_trading/pa.py
pa_trading/pb.py
pa_trading/ro.py
pa_trading/tr.py
pa_trading-0.8.dist-info/entry_points.txt
pa_trading-0.8.dist-info/LICENSE
pa_trading-0.8.dist-info/METADATA
pa_trading-0.8.dist-info/WHEEL
pa_trading-0.8.dist-info/RECORD
